linien_server/__init__.py
linien_server/acquisition.py
linien_server/cli.py
linien_server/csr.py
linien_server/csrmap.py
linien_server/gateware.bin
linien_server/iir_coeffs.py
linien_server/influxdb.py
linien_server/linien-server.service
linien_server/mdio-tool
linien_server/mdio_tool.py
linien_server/noise_analysis.py
linien_server/parameters.py
linien_server/registers.py
linien_server/server.py
linien_server/autolock/__init__.py
linien_server/autolock/algorithm_selection.py
linien_server/autolock/autolock.py
linien_server/autolock/robust.py
linien_server/autolock/simple.py
linien_server/autolock/utils.py
linien_server/optimization/__init__.py
linien_server/optimization/approach_line.py
linien_server/optimization/engine.py
linien_server/optimization/general.py
linien_server/optimization/optimization.py
linien_server/optimization/utils.py
linien_server-2.1.0.dist-info/METADATA
linien_server-2.1.0.dist-info/WHEEL
linien_server-2.1.0.dist-info/entry_points.txt
linien_server-2.1.0.dist-info/top_level.txt
linien_server-2.1.0.dist-info/RECORD
