Metadata-Version: 2.1
Name: linien-server
Version: 2.1.0
Summary: Server components of the Linien spectroscopy lock application.
Author-email: Benjamin Wiegand <benjamin.wiegand@physik.hu-berlin.de>, Bastian Leykauf <leykauf@physik.hu-berlin.de>, Robert Jördens <rj@quartiq.de>, Christian Freier <christian.freier@gmail.com>, Doron Behar <doron.behar@gmail.com>
Maintainer-email: Bastian Leykauf <leykauf@physik.hu-berlin.de>
Project-URL: Homepage, https://github.com/linien-org/linien
Classifier: Programming Language :: Python :: 3
Classifier: License :: OSI Approved :: GNU General Public License v3 (GPLv3)
Classifier: Operating System :: OS Independent
Requires-Python: >=3.10
Requires-Dist: cma <4.0,>=3.0.3
Requires-Dist: fire >=0.6.0
Requires-Dist: influxdb-client[ciso] <2.0,>=1.9
Requires-Dist: pylpsd >=0.1.4
Requires-Dist: linien-common ==2.1.0
Requires-Dist: pyrp3 <3.0,>=2.1.0 ; platform_machine == "armv7l"
